[
  {
    "line": 1,
    "elements": [
      {
        "line": 4,
        "name": "",
        "description": "",
        "type": "background",
        "keyword": "Background",
        "steps": [
          {
            "result": {
              "duration": 6391042000,
              "status": "passed"
            },
            "line": 5,
            "name": "I am on the main page",
            "match": {
              "location": "us.buyget.step_definitions.mainPageTopTabs.i_am_on_the_main_page()"
            },
            "keyword": "Given "
          }
        ]
      },
      {
        "start_timestamp": "2021-12-11T18:30:00.653Z",
        "line": 7,
        "name": "",
        "description": "",
        "id": "main-page-bottom-tabs-functionality;",
        "type": "scenario",
        "keyword": "Scenario",
        "steps": [
          {
            "result": {
              "duration": 1339973000,
              "status": "passed"
            },
            "line": 8,
            "name": "I click on search tab",
            "match": {
              "location": "us.buyget.step_definitions.MainPageBottomTabs.i_click_on_search_tab()"
            },
            "keyword": "When "
          },
          {
            "result": {
              "duration": 20520000,
              "status": "passed"
            },
            "line": 9,
            "name": "I should be able to navigate to search page",
            "match": {
              "location": "us.buyget.step_definitions.MainPageBottomTabs.i_should_be_able_to_navigate_to_search_page()"
            },
            "keyword": "Then "
          }
        ],
        "tags": [
          {
            "name": "@smoke"
          }
        ]
      },
      {
        "line": 4,
        "name": "",
        "description": "",
        "type": "background",
        "keyword": "Background",
        "steps": [
          {
            "result": {
              "duration": 1156382000,
              "status": "passed"
            },
            "line": 5,
            "name": "I am on the main page",
            "match": {
              "location": "us.buyget.step_definitions.mainPageTopTabs.i_am_on_the_main_page()"
            },
            "keyword": "Given "
          }
        ]
      },
      {
        "start_timestamp": "2021-12-11T18:30:08.460Z",
        "line": 11,
        "name": "",
        "description": "",
        "id": "main-page-bottom-tabs-functionality;",
        "type": "scenario",
        "keyword": "Scenario",
        "steps": [
          {
            "result": {
              "duration": 805728000,
              "status": "passed"
            },
            "line": 12,
            "name": "I click on contact tab",
            "match": {
              "location": "us.buyget.step_definitions.MainPageBottomTabs.i_click_on_contact_tab()"
            },
            "keyword": "When "
          },
          {
            "result": {
              "duration": 13916000,
              "status": "passed"
            },
            "line": 13,
            "name": "I should be able to navigate to contact page",
            "match": {
              "location": "us.buyget.step_definitions.MainPageBottomTabs.i_should_be_able_to_navigate_to_contact_page()"
            },
            "keyword": "Then "
          }
        ],
        "tags": [
          {
            "name": "@smoke"
          }
        ]
      },
      {
        "line": 4,
        "name": "",
        "description": "",
        "type": "background",
        "keyword": "Background",
        "steps": [
          {
            "result": {
              "duration": 1114230000,
              "status": "passed"
            },
            "line": 5,
            "name": "I am on the main page",
            "match": {
              "location": "us.buyget.step_definitions.mainPageTopTabs.i_am_on_the_main_page()"
            },
            "keyword": "Given "
          }
        ]
      },
      {
        "start_timestamp": "2021-12-11T18:30:10.443Z",
        "line": 15,
        "name": "",
        "description": "",
        "id": "main-page-bottom-tabs-functionality;",
        "type": "scenario",
        "keyword": "Scenario",
        "steps": [
          {
            "result": {
              "duration": 1526313000,
              "status": "passed"
            },
            "line": 16,
            "name": "I click on terms of service tab",
            "match": {
              "location": "us.buyget.step_definitions.MainPageBottomTabs.i_click_on_terms_of_service_tab()"
            },
            "keyword": "When "
          },
          {
            "result": {
              "duration": 18023000,
              "status": "passed"
            },
            "line": 17,
            "name": "I should be able to navigate to terms of service page",
            "match": {
              "location": "us.buyget.step_definitions.MainPageBottomTabs.i_should_be_able_to_navigate_to_terms_of_service_page()"
            },
            "keyword": "Then "
          }
        ],
        "tags": [
          {
            "name": "@smoke"
          }
        ]
      },
      {
        "line": 4,
        "name": "",
        "description": "",
        "type": "background",
        "keyword": "Background",
        "steps": [
          {
            "result": {
              "duration": 1115141000,
              "status": "passed"
            },
            "line": 5,
            "name": "I am on the main page",
            "match": {
              "location": "us.buyget.step_definitions.mainPageTopTabs.i_am_on_the_main_page()"
            },
            "keyword": "Given "
          }
        ]
      },
      {
        "start_timestamp": "2021-12-11T18:30:13.107Z",
        "line": 19,
        "name": "",
        "description": "",
        "id": "main-page-bottom-tabs-functionality;",
        "type": "scenario",
        "keyword": "Scenario",
        "steps": [
          {
            "result": {
              "duration": 1223022000,
              "status": "passed"
            },
            "line": 20,
            "name": "I click on refund policy tab",
            "match": {
              "location": "us.buyget.step_definitions.MainPageBottomTabs.i_click_on_refund_policy_tab()"
            },
            "keyword": "When "
          },
          {
            "result": {
              "duration": 20325000,
              "status": "passed"
            },
            "line": 21,
            "name": "I should be able to navigate to refund policy page",
            "match": {
              "location": "us.buyget.step_definitions.MainPageBottomTabs.i_should_be_able_to_navigate_to_refund_policy_page()"
            },
            "keyword": "Then "
          }
        ],
        "tags": [
          {
            "name": "@smoke"
          }
        ]
      },
      {
        "line": 4,
        "name": "",
        "description": "",
        "type": "background",
        "keyword": "Background",
        "steps": [
          {
            "result": {
              "duration": 875796000,
              "status": "passed"
            },
            "line": 5,
            "name": "I am on the main page",
            "match": {
              "location": "us.buyget.step_definitions.mainPageTopTabs.i_am_on_the_main_page()"
            },
            "keyword": "Given "
          }
        ]
      },
      {
        "start_timestamp": "2021-12-11T18:30:15.472Z",
        "line": 23,
        "name": "",
        "description": "",
        "id": "main-page-bottom-tabs-functionality;",
        "type": "scenario",
        "keyword": "Scenario",
        "steps": [
          {
            "result": {
              "duration": 902625000,
              "status": "passed"
            },
            "line": 24,
            "name": "I click on privacy policy tab",
            "match": {
              "location": "us.buyget.step_definitions.MainPageBottomTabs.i_click_on_privacy_policy_tab()"
            },
            "keyword": "When "
          },
          {
            "result": {
              "duration": 11413000,
              "status": "passed"
            },
            "line": 25,
            "name": "I should be able to navigate to privacy policy page",
            "match": {
              "location": "us.buyget.step_definitions.MainPageBottomTabs.i_should_be_able_to_navigate_to_privacy_policy_page()"
            },
            "keyword": "Then "
          }
        ],
        "tags": [
          {
            "name": "@smoke"
          }
        ]
      }
    ],
    "name": "Main page bottom tabs functionality",
    "description": "  As a user, when I click on the bottom tabs I should be able to access to these particular item pages.",
    "id": "main-page-bottom-tabs-functionality",
    "keyword": "Feature",
    "uri": "file:src/test/resources/features/mainPageBottomTabs.feature",
    "tags": []
  },
  {
    "line": 1,
    "elements": [
      {
        "line": 4,
        "name": "",
        "description": "",
        "type": "background",
        "keyword": "Background",
        "steps": [
          {
            "result": {
              "duration": 1078176000,
              "status": "passed"
            },
            "line": 5,
            "name": "I am on the main page",
            "match": {
              "location": "us.buyget.step_definitions.mainPageTopTabs.i_am_on_the_main_page()"
            },
            "keyword": "Given "
          }
        ]
      },
      {
        "start_timestamp": "2021-12-11T18:30:17.268Z",
        "line": 8,
        "name": "",
        "description": "",
        "id": "main-page-headers-functionality;",
        "type": "scenario",
        "keyword": "Scenario",
        "steps": [
          {
            "result": {
              "duration": 1039631000,
              "status": "passed"
            },
            "line": 9,
            "name": "I click on the NEMA - Best Prices header",
            "match": {
              "location": "us.buyget.step_definitions.MainPageHeaders.i_click_on_the_nema_best_prices_header()"
            },
            "keyword": "When "
          },
          {
            "result": {
              "duration": 14873000,
              "status": "passed"
            },
            "line": 10,
            "name": "I should be able to navigate to NEMA - Best Prices page",
            "match": {
              "location": "us.buyget.step_definitions.MainPageHeaders.i_should_be_able_to_navigate_to_nema_best_prices_page()"
            },
            "keyword": "Then "
          }
        ],
        "tags": [
          {
            "name": "@smoke"
          }
        ]
      },
      {
        "line": 4,
        "name": "",
        "description": "",
        "type": "background",
        "keyword": "Background",
        "steps": [
          {
            "result": {
              "duration": 1165634000,
              "status": "passed"
            },
            "line": 5,
            "name": "I am on the main page",
            "match": {
              "location": "us.buyget.step_definitions.mainPageTopTabs.i_am_on_the_main_page()"
            },
            "keyword": "Given "
          }
        ]
      },
      {
        "start_timestamp": "2021-12-11T18:30:19.413Z",
        "line": 13,
        "name": "",
        "description": "",
        "id": "main-page-headers-functionality;",
        "type": "scenario",
        "keyword": "Scenario",
        "steps": [
          {
            "result": {
              "duration": 1151235000,
              "status": "passed"
            },
            "line": 14,
            "name": "I click on the Fresh \u0026 Frozen Halal Meat header",
            "match": {
              "location": "us.buyget.step_definitions.MainPageHeaders.i_click_on_the_fresh_frozen_halal_meat_header()"
            },
            "keyword": "When "
          },
          {
            "result": {
              "duration": 27869000,
              "status": "passed"
            },
            "line": 15,
            "name": "I should be able to navigate to Fresh \u0026 Frozen Halal Meat page",
            "match": {
              "location": "us.buyget.step_definitions.MainPageHeaders.i_should_be_able_to_navigate_to_fresh_frozen_halal_meat_page()"
            },
            "keyword": "Then "
          }
        ],
        "tags": [
          {
            "name": "@smoke"
          }
        ]
      },
      {
        "line": 4,
        "name": "",
        "description": "",
        "type": "background",
        "keyword": "Background",
        "steps": [
          {
            "result": {
              "duration": 1179816000,
              "status": "passed"
            },
            "line": 5,
            "name": "I am on the main page",
            "match": {
              "location": "us.buyget.step_definitions.mainPageTopTabs.i_am_on_the_main_page()"
            },
            "keyword": "Given "
          }
        ]
      },
      {
        "start_timestamp": "2021-12-11T18:30:21.762Z",
        "line": 18,
        "name": "",
        "description": "",
        "id": "main-page-headers-functionality;",
        "type": "scenario",
        "keyword": "Scenario",
        "steps": [
          {
            "result": {
              "duration": 1483530000,
              "status": "passed"
            },
            "line": 19,
            "name": "I click on the Best Selling Title",
            "match": {
              "location": "us.buyget.step_definitions.MainPageHeaders.i_click_on_the_best_selling_title()"
            },
            "keyword": "When "
          },
          {
            "result": {
              "duration": 12799000,
              "status": "passed"
            },
            "line": 20,
            "name": "I should be able to navigate to Best Selling page",
            "match": {
              "location": "us.buyget.step_definitions.MainPageHeaders.i_should_be_able_to_navigate_to_best_selling_page()"
            },
            "keyword": "Then "
          }
        ],
        "tags": [
          {
            "name": "@smoke"
          }
        ]
      },
      {
        "line": 4,
        "name": "",
        "description": "",
        "type": "background",
        "keyword": "Background",
        "steps": [
          {
            "result": {
              "duration": 1157137000,
              "status": "passed"
            },
            "line": 5,
            "name": "I am on the main page",
            "match": {
              "location": "us.buyget.step_definitions.mainPageTopTabs.i_am_on_the_main_page()"
            },
            "keyword": "Given "
          }
        ]
      },
      {
        "start_timestamp": "2021-12-11T18:30:24.445Z",
        "line": 23,
        "name": "",
        "description": "",
        "id": "main-page-headers-functionality;",
        "type": "scenario",
        "keyword": "Scenario",
        "steps": [
          {
            "result": {
              "duration": 872365000,
              "status": "passed"
            },
            "line": 24,
            "name": "I click on the Homemade header",
            "match": {
              "location": "us.buyget.step_definitions.MainPageHeaders.i_click_on_the_homemade_header()"
            },
            "keyword": "When "
          },
          {
            "result": {
              "duration": 13585000,
              "status": "passed"
            },
            "line": 25,
            "name": "I should be able to navigate to Homemade page",
            "match": {
              "location": "us.buyget.step_definitions.mainPageTopTabs.i_should_be_able_to_navigate_to_homemade_page()"
            },
            "keyword": "Then "
          }
        ],
        "tags": [
          {
            "name": "@smoke"
          }
        ]
      },
      {
        "line": 4,
        "name": "",
        "description": "",
        "type": "background",
        "keyword": "Background",
        "steps": [
          {
            "result": {
              "duration": 1140354000,
              "status": "passed"
            },
            "line": 5,
            "name": "I am on the main page",
            "match": {
              "location": "us.buyget.step_definitions.mainPageTopTabs.i_am_on_the_main_page()"
            },
            "keyword": "Given "
          }
        ]
      },
      {
        "start_timestamp": "2021-12-11T18:30:26.493Z",
        "line": 28,
        "name": "",
        "description": "",
        "id": "main-page-headers-functionality;",
        "type": "scenario",
        "keyword": "Scenario",
        "steps": [
          {
            "result": {
              "duration": 2388573000,
              "status": "passed"
            },
            "line": 29,
            "name": "I click on the Dairy Products header",
            "match": {
              "location": "us.buyget.step_definitions.MainPageHeaders.i_click_on_the_dairy_products_header()"
            },
            "keyword": "When "
          },
          {
            "result": {
              "duration": 14523000,
              "status": "passed"
            },
            "line": 30,
            "name": "I should be able to navigate to Dairy Products page",
            "match": {
              "location": "us.buyget.step_definitions.MainPageHeaders.i_should_be_able_to_navigate_to_dairy_products_page()"
            },
            "keyword": "Then "
          }
        ],
        "tags": [
          {
            "name": "@smoke"
          }
        ]
      },
      {
        "line": 4,
        "name": "",
        "description": "",
        "type": "background",
        "keyword": "Background",
        "steps": [
          {
            "result": {
              "duration": 1182551000,
              "status": "passed"
            },
            "line": 5,
            "name": "I am on the main page",
            "match": {
              "location": "us.buyget.step_definitions.mainPageTopTabs.i_am_on_the_main_page()"
            },
            "keyword": "Given "
          }
        ]
      },
      {
        "start_timestamp": "2021-12-11T18:30:30.040Z",
        "line": 32,
        "name": "",
        "description": "",
        "id": "main-page-headers-functionality;",
        "type": "scenario",
        "keyword": "Scenario",
        "steps": [
          {
            "result": {
              "duration": 3161123000,
              "status": "passed"
            },
            "line": 33,
            "name": "I click on the Deli Meat header",
            "match": {
              "location": "us.buyget.step_definitions.MainPageHeaders.i_click_on_the_deli_meat_header()"
            },
            "keyword": "When "
          },
          {
            "result": {
              "duration": 51385000,
              "status": "passed"
            },
            "line": 34,
            "name": "I should be able to navigate to Deli Meat page",
            "match": {
              "location": "us.buyget.step_definitions.MainPageHeaders.i_should_be_able_to_navigate_to_deli_meat_page()"
            },
            "keyword": "Then "
          }
        ],
        "tags": [
          {
            "name": "@smoke"
          }
        ]
      },
      {
        "line": 4,
        "name": "",
        "description": "",
        "type": "background",
        "keyword": "Background",
        "steps": [
          {
            "result": {
              "duration": 1319987000,
              "status": "passed"
            },
            "line": 5,
            "name": "I am on the main page",
            "match": {
              "location": "us.buyget.step_definitions.mainPageTopTabs.i_am_on_the_main_page()"
            },
            "keyword": "Given "
          }
        ]
      },
      {
        "start_timestamp": "2021-12-11T18:30:34.439Z",
        "line": 36,
        "name": "",
        "description": "",
        "id": "main-page-headers-functionality;",
        "type": "scenario",
        "keyword": "Scenario",
        "steps": [
          {
            "result": {
              "duration": 983824000,
              "status": "passed"
            },
            "line": 37,
            "name": "I click on the Pantry header",
            "match": {
              "location": "us.buyget.step_definitions.MainPageHeaders.i_click_on_the_pantry_header()"
            },
            "keyword": "When "
          },
          {
            "result": {
              "duration": 18222000,
              "status": "passed"
            },
            "line": 38,
            "name": "I should be able to navigate to Pantry page",
            "match": {
              "location": "us.buyget.step_definitions.mainPageTopTabs.i_should_be_able_to_navigate_to_pantry_page()"
            },
            "keyword": "Then "
          }
        ],
        "tags": [
          {
            "name": "@smoke"
          }
        ]
      },
      {
        "line": 4,
        "name": "",
        "description": "",
        "type": "background",
        "keyword": "Background",
        "steps": [
          {
            "result": {
              "duration": 1150013000,
              "status": "passed"
            },
            "line": 5,
            "name": "I am on the main page",
            "match": {
              "location": "us.buyget.step_definitions.mainPageTopTabs.i_am_on_the_main_page()"
            },
            "keyword": "Given "
          }
        ]
      },
      {
        "start_timestamp": "2021-12-11T18:30:36.764Z",
        "line": 40,
        "name": "",
        "description": "",
        "id": "main-page-headers-functionality;",
        "type": "scenario",
        "keyword": "Scenario",
        "steps": [
          {
            "result": {
              "duration": 2331139000,
              "status": "passed"
            },
            "line": 41,
            "name": "I click on the Beverages header",
            "match": {
              "location": "us.buyget.step_definitions.MainPageHeaders.i_click_on_the_beverages_header()"
            },
            "keyword": "When "
          },
          {
            "result": {
              "duration": 19370000,
              "status": "passed"
            },
            "line": 42,
            "name": "I should be able to navigate to beverages page",
            "match": {
              "location": "us.buyget.step_definitions.mainPageTopTabs.i_should_be_able_to_navigate_to_beverages_page()"
            },
            "keyword": "Then "
          }
        ],
        "tags": [
          {
            "name": "@smoke"
          }
        ]
      },
      {
        "line": 4,
        "name": "",
        "description": "",
        "type": "background",
        "keyword": "Background",
        "steps": [
          {
            "result": {
              "duration": 2285217000,
              "status": "passed"
            },
            "line": 5,
            "name": "I am on the main page",
            "match": {
              "location": "us.buyget.step_definitions.mainPageTopTabs.i_am_on_the_main_page()"
            },
            "keyword": "Given "
          }
        ]
      },
      {
        "start_timestamp": "2021-12-11T18:30:40.268Z",
        "line": 44,
        "name": "",
        "description": "",
        "id": "main-page-headers-functionality;",
        "type": "scenario",
        "keyword": "Scenario",
        "steps": [
          {
            "result": {
              "duration": 1095925000,
              "status": "passed"
            },
            "line": 45,
            "name": "I click on the Chocolate, Candy \u0026 Snacks header",
            "match": {
              "location": "us.buyget.step_definitions.MainPageHeaders.i_click_on_the_chocolate_candy_snacks_header()"
            },
            "keyword": "When "
          },
          {
            "result": {
              "duration": 20035000,
              "status": "passed"
            },
            "line": 46,
            "name": "I should be able to navigate to Chocolate, Candy \u0026 Snacks page",
            "match": {
              "location": "us.buyget.step_definitions.mainPageTopTabs.i_should_be_able_to_navigate_to_confectionary_page()"
            },
            "keyword": "Then "
          }
        ],
        "tags": [
          {
            "name": "@smoke"
          }
        ]
      },
      {
        "line": 4,
        "name": "",
        "description": "",
        "type": "background",
        "keyword": "Background",
        "steps": [
          {
            "result": {
              "duration": 1163182000,
              "status": "passed"
            },
            "line": 5,
            "name": "I am on the main page",
            "match": {
              "location": "us.buyget.step_definitions.mainPageTopTabs.i_am_on_the_main_page()"
            },
            "keyword": "Given "
          }
        ]
      },
      {
        "start_timestamp": "2021-12-11T18:30:43.673Z",
        "line": 48,
        "name": "",
        "description": "",
        "id": "main-page-headers-functionality;",
        "type": "scenario",
        "keyword": "Scenario",
        "steps": [
          {
            "result": {
              "duration": 1142909000,
              "status": "passed"
            },
            "line": 49,
            "name": "I click on the Coffee \u0026 Tea header",
            "match": {
              "location": "us.buyget.step_definitions.MainPageHeaders.i_click_on_the_coffee_tea_header()"
            },
            "keyword": "When "
          },
          {
            "result": {
              "duration": 15762000,
              "status": "passed"
            },
            "line": 50,
            "name": "I should be able to navigate to coffee-tea page",
            "match": {
              "location": "us.buyget.step_definitions.mainPageTopTabs.i_should_be_able_to_navigate_to_coffee_tea_page()"
            },
            "keyword": "Then "
          }
        ],
        "tags": [
          {
            "name": "@smoke"
          }
        ]
      },
      {
        "line": 4,
        "name": "",
        "description": "",
        "type": "background",
        "keyword": "Background",
        "steps": [
          {
            "result": {
              "duration": 1206172000,
              "status": "passed"
            },
            "line": 5,
            "name": "I am on the main page",
            "match": {
              "location": "us.buyget.step_definitions.mainPageTopTabs.i_am_on_the_main_page()"
            },
            "keyword": "Given "
          }
        ]
      },
      {
        "start_timestamp": "2021-12-11T18:30:45.998Z",
        "line": 52,
        "name": "",
        "description": "",
        "id": "main-page-headers-functionality;",
        "type": "scenario",
        "keyword": "Scenario",
        "steps": [
          {
            "result": {
              "duration": 1811962000,
              "status": "passed"
            },
            "line": 53,
            "name": "I click on the Dried Fruits \u0026 Nuts header",
            "match": {
              "location": "us.buyget.step_definitions.MainPageHeaders.i_click_on_the_dried_fruits_nuts_header()"
            },
            "keyword": "When "
          },
          {
            "result": {
              "duration": 15242000,
              "status": "passed"
            },
            "line": 54,
            "name": "I should be able to navigate to dried-fruit-nuts page",
            "match": {
              "location": "us.buyget.step_definitions.mainPageTopTabs.i_should_be_able_to_navigate_to_dried_fruit_nuts_page()"
            },
            "keyword": "Then "
          }
        ],
        "tags": [
          {
            "name": "@smoke"
          }
        ]
      },
      {
        "line": 4,
        "name": "",
        "description": "",
        "type": "background",
        "keyword": "Background",
        "steps": [
          {
            "result": {
              "duration": 1151692000,
              "status": "passed"
            },
            "line": 5,
            "name": "I am on the main page",
            "match": {
              "location": "us.buyget.step_definitions.mainPageTopTabs.i_am_on_the_main_page()"
            },
            "keyword": "Given "
          }
        ]
      },
      {
        "start_timestamp": "2021-12-11T18:30:49.036Z",
        "line": 56,
        "name": "",
        "description": "",
        "id": "main-page-headers-functionality;",
        "type": "scenario",
        "keyword": "Scenario",
        "steps": [
          {
            "result": {
              "duration": 2068133000,
              "status": "passed"
            },
            "line": 57,
            "name": "I click on the Breads \u0026 Pastries header",
            "match": {
              "location": "us.buyget.step_definitions.MainPageHeaders.i_click_on_the_breads_pastries_header()"
            },
            "keyword": "When "
          },
          {
            "result": {
              "duration": 22027000,
              "status": "passed"
            },
            "line": 58,
            "name": "I should be able to navigate to breads-pastries page",
            "match": {
              "location": "us.buyget.step_definitions.mainPageTopTabs.i_should_be_able_to_navigate_to_breads_pastries_page()"
            },
            "keyword": "Then "
          }
        ],
        "tags": [
          {
            "name": "@smoke"
          }
        ]
      },
      {
        "line": 4,
        "name": "",
        "description": "",
        "type": "background",
        "keyword": "Background",
        "steps": [
          {
            "result": {
              "duration": 1772678000,
              "status": "passed"
            },
            "line": 5,
            "name": "I am on the main page",
            "match": {
              "location": "us.buyget.step_definitions.mainPageTopTabs.i_am_on_the_main_page()"
            },
            "keyword": "Given "
          }
        ]
      },
      {
        "start_timestamp": "2021-12-11T18:30:52.281Z",
        "line": 60,
        "name": "",
        "description": "",
        "id": "main-page-headers-functionality;",
        "type": "scenario",
        "keyword": "Scenario",
        "steps": [
          {
            "result": {
              "duration": 995399000,
              "status": "passed"
            },
            "line": 61,
            "name": "I click on the Frozen header",
            "match": {
              "location": "us.buyget.step_definitions.MainPageHeaders.i_click_on_the_frozen_header()"
            },
            "keyword": "When "
          },
          {
            "result": {
              "duration": 14244000,
              "status": "passed"
            },
            "line": 62,
            "name": "I should be able to navigate to frozen page",
            "match": {
              "location": "us.buyget.step_definitions.mainPageTopTabs.i_should_be_able_to_navigate_to_frozen_page()"
            },
            "keyword": "Then "
          }
        ],
        "tags": [
          {
            "name": "@smoke"
          }
        ]
      }
    ],
    "name": "Main page headers functionality",
    "description": "  As a user, when I click on the header title, I should be able to access to these particular title pages.",
    "id": "main-page-headers-functionality",
    "keyword": "Feature",
    "uri": "file:src/test/resources/features/mainPageHeaders.feature",
    "tags": []
  },
  {
    "line": 1,
    "elements": [
      {
        "line": 5,
        "name": "",
        "description": "",
        "type": "background",
        "keyword": "Background",
        "steps": [
          {
            "result": {
              "duration": 1254057000,
              "status": "passed"
            },
            "line": 6,
            "name": "I am on the main page",
            "match": {
              "location": "us.buyget.step_definitions.mainPageTopTabs.i_am_on_the_main_page()"
            },
            "keyword": "Given "
          }
        ]
      },
      {
        "start_timestamp": "2021-12-11T18:30:55.067Z",
        "line": 8,
        "name": "",
        "description": "",
        "id": "main-page-top-tabs-functionality;",
        "type": "scenario",
        "keyword": "Scenario",
        "steps": [
          {
            "result": {
              "duration": 834610000,
              "status": "passed"
            },
            "line": 9,
            "name": "I click on the Homemade tab",
            "match": {
              "location": "us.buyget.step_definitions.mainPageTopTabs.i_click_on_the_homemade_tab()"
            },
            "keyword": "When "
          },
          {
            "result": {
              "duration": 12860000,
              "status": "passed"
            },
            "line": 10,
            "name": "I should be able to navigate to Homemade page",
            "match": {
              "location": "us.buyget.step_definitions.mainPageTopTabs.i_should_be_able_to_navigate_to_homemade_page()"
            },
            "keyword": "Then "
          }
        ],
        "tags": [
          {
            "name": "@smoke"
          }
        ]
      },
      {
        "line": 5,
        "name": "",
        "description": "",
        "type": "background",
        "keyword": "Background",
        "steps": [
          {
            "result": {
              "duration": 1152355000,
              "status": "passed"
            },
            "line": 6,
            "name": "I am on the main page",
            "match": {
              "location": "us.buyget.step_definitions.mainPageTopTabs.i_am_on_the_main_page()"
            },
            "keyword": "Given "
          }
        ]
      },
      {
        "start_timestamp": "2021-12-11T18:30:57.175Z",
        "line": 12,
        "name": "",
        "description": "",
        "id": "main-page-top-tabs-functionality;",
        "type": "scenario",
        "keyword": "Scenario",
        "steps": [
          {
            "result": {
              "duration": 1020524000,
              "status": "passed"
            },
            "line": 13,
            "name": "I click on the Dairy tab",
            "match": {
              "location": "us.buyget.step_definitions.mainPageTopTabs.i_click_on_the_dairy_tab()"
            },
            "keyword": "When "
          },
          {
            "result": {
              "duration": 13932000,
              "status": "passed"
            },
            "line": 14,
            "name": "I should be able to navigate to Dairy page",
            "match": {
              "location": "us.buyget.step_definitions.mainPageTopTabs.i_should_be_able_to_navigate_to_dairy_page()"
            },
            "keyword": "Then "
          }
        ],
        "tags": [
          {
            "name": "@smoke"
          }
        ]
      },
      {
        "line": 5,
        "name": "",
        "description": "",
        "type": "background",
        "keyword": "Background",
        "steps": [
          {
            "result": {
              "duration": 1207053000,
              "status": "passed"
            },
            "line": 6,
            "name": "I am on the main page",
            "match": {
              "location": "us.buyget.step_definitions.mainPageTopTabs.i_am_on_the_main_page()"
            },
            "keyword": "Given "
          }
        ]
      },
      {
        "start_timestamp": "2021-12-11T18:30:59.365Z",
        "line": 16,
        "name": "",
        "description": "",
        "id": "main-page-top-tabs-functionality;",
        "type": "scenario",
        "keyword": "Scenario",
        "steps": [
          {
            "result": {
              "duration": 955345000,
              "status": "passed"
            },
            "line": 17,
            "name": "I click on the Pantry tab",
            "match": {
              "location": "us.buyget.step_definitions.mainPageTopTabs.i_click_on_the_pantry_tab()"
            },
            "keyword": "When "
          },
          {
            "result": {
              "duration": 13634000,
              "status": "passed"
            },
            "line": 18,
            "name": "I should be able to navigate to Pantry page",
            "match": {
              "location": "us.buyget.step_definitions.mainPageTopTabs.i_should_be_able_to_navigate_to_pantry_page()"
            },
            "keyword": "Then "
          }
        ],
        "tags": [
          {
            "name": "@smoke"
          }
        ]
      },
      {
        "line": 5,
        "name": "",
        "description": "",
        "type": "background",
        "keyword": "Background",
        "steps": [
          {
            "result": {
              "duration": 1229930000,
              "status": "passed"
            },
            "line": 6,
            "name": "I am on the main page",
            "match": {
              "location": "us.buyget.step_definitions.mainPageTopTabs.i_am_on_the_main_page()"
            },
            "keyword": "Given "
          }
        ]
      },
      {
        "start_timestamp": "2021-12-11T18:31:01.544Z",
        "line": 20,
        "name": "",
        "description": "",
        "id": "main-page-top-tabs-functionality;",
        "type": "scenario",
        "keyword": "Scenario",
        "steps": [
          {
            "result": {
              "duration": 1518104000,
              "status": "passed"
            },
            "line": 21,
            "name": "I click on the Canned Food tab",
            "match": {
              "location": "us.buyget.step_definitions.mainPageTopTabs.i_click_on_the_canned_food_tab()"
            },
            "keyword": "When "
          },
          {
            "result": {
              "duration": 37475000,
              "status": "passed"
            },
            "line": 22,
            "name": "I should be able to navigate to canned-food page",
            "match": {
              "location": "us.buyget.step_definitions.mainPageTopTabs.i_should_be_able_to_navigate_to_canned_food_page()"
            },
            "keyword": "Then "
          }
        ],
        "tags": [
          {
            "name": "@smoke"
          }
        ]
      },
      {
        "line": 5,
        "name": "",
        "description": "",
        "type": "background",
        "keyword": "Background",
        "steps": [
          {
            "result": {
              "duration": 1158417000,
              "status": "passed"
            },
            "line": 6,
            "name": "I am on the main page",
            "match": {
              "location": "us.buyget.step_definitions.mainPageTopTabs.i_am_on_the_main_page()"
            },
            "keyword": "Given "
          }
        ]
      },
      {
        "start_timestamp": "2021-12-11T18:31:04.332Z",
        "line": 24,
        "name": "",
        "description": "",
        "id": "main-page-top-tabs-functionality;",
        "type": "scenario",
        "keyword": "Scenario",
        "steps": [
          {
            "result": {
              "duration": 354369000,
              "status": "passed"
            },
            "line": 25,
            "name": "I click on the Confectionary tab",
            "match": {
              "location": "us.buyget.step_definitions.mainPageTopTabs.i_click_on_the_confectionary_tab()"
            },
            "keyword": "When "
          },
          {
            "result": {
              "duration": 48628000,
              "status": "passed"
            },
            "line": 26,
            "name": "I should be able to navigate to Chocolate, Candy \u0026 Snacks page",
            "match": {
              "location": "us.buyget.step_definitions.mainPageTopTabs.i_should_be_able_to_navigate_to_confectionary_page()"
            },
            "keyword": "Then "
          }
        ],
        "tags": [
          {
            "name": "@smoke"
          }
        ]
      },
      {
        "line": 5,
        "name": "",
        "description": "",
        "type": "background",
        "keyword": "Background",
        "steps": [
          {
            "result": {
              "duration": 1250421000,
              "status": "passed"
            },
            "line": 6,
            "name": "I am on the main page",
            "match": {
              "location": "us.buyget.step_definitions.mainPageTopTabs.i_am_on_the_main_page()"
            },
            "keyword": "Given "
          }
        ]
      },
      {
        "start_timestamp": "2021-12-11T18:31:05.897Z",
        "line": 28,
        "name": "",
        "description": "",
        "id": "main-page-top-tabs-functionality;",
        "type": "scenario",
        "keyword": "Scenario",
        "steps": [
          {
            "result": {
              "duration": 1568216000,
              "status": "passed"
            },
            "line": 29,
            "name": "I click on the Coffee \u0026 Tea tab",
            "match": {
              "location": "us.buyget.step_definitions.mainPageTopTabs.i_click_on_the_coffee_tea_tab()"
            },
            "keyword": "When "
          },
          {
            "result": {
              "duration": 14611000,
              "status": "passed"
            },
            "line": 30,
            "name": "I should be able to navigate to coffee-tea page",
            "match": {
              "location": "us.buyget.step_definitions.mainPageTopTabs.i_should_be_able_to_navigate_to_coffee_tea_page()"
            },
            "keyword": "Then "
          }
        ],
        "tags": [
          {
            "name": "@smoke"
          }
        ]
      },
      {
        "line": 5,
        "name": "",
        "description": "",
        "type": "background",
        "keyword": "Background",
        "steps": [
          {
            "result": {
              "duration": 1158288000,
              "status": "passed"
            },
            "line": 6,
            "name": "I am on the main page",
            "match": {
              "location": "us.buyget.step_definitions.mainPageTopTabs.i_am_on_the_main_page()"
            },
            "keyword": "Given "
          }
        ]
      },
      {
        "start_timestamp": "2021-12-11T18:31:08.733Z",
        "line": 32,
        "name": "",
        "description": "",
        "id": "main-page-top-tabs-functionality;",
        "type": "scenario",
        "keyword": "Scenario",
        "steps": [
          {
            "result": {
              "duration": 981521000,
              "status": "passed"
            },
            "line": 33,
            "name": "I click on the Dried Fruit \u0026 Nuts tab",
            "match": {
              "location": "us.buyget.step_definitions.mainPageTopTabs.i_click_on_the_dried_fruit_nuts_tab()"
            },
            "keyword": "When "
          },
          {
            "result": {
              "duration": 14035000,
              "status": "passed"
            },
            "line": 34,
            "name": "I should be able to navigate to dried-fruit-nuts page",
            "match": {
              "location": "us.buyget.step_definitions.mainPageTopTabs.i_should_be_able_to_navigate_to_dried_fruit_nuts_page()"
            },
            "keyword": "Then "
          }
        ],
        "tags": [
          {
            "name": "@smoke"
          }
        ]
      },
      {
        "line": 5,
        "name": "",
        "description": "",
        "type": "background",
        "keyword": "Background",
        "steps": [
          {
            "result": {
              "duration": 1141194000,
              "status": "passed"
            },
            "line": 6,
            "name": "I am on the main page",
            "match": {
              "location": "us.buyget.step_definitions.mainPageTopTabs.i_am_on_the_main_page()"
            },
            "keyword": "Given "
          }
        ]
      },
      {
        "start_timestamp": "2021-12-11T18:31:10.890Z",
        "line": 36,
        "name": "",
        "description": "",
        "id": "main-page-top-tabs-functionality;",
        "type": "scenario",
        "keyword": "Scenario",
        "steps": [
          {
            "result": {
              "duration": 1038062000,
              "status": "passed"
            },
            "line": 37,
            "name": "I click on the Beverages  tab",
            "match": {
              "location": "us.buyget.step_definitions.mainPageTopTabs.i_click_on_the_beverages_tab()"
            },
            "keyword": "When "
          },
          {
            "result": {
              "duration": 13697000,
              "status": "passed"
            },
            "line": 38,
            "name": "I should be able to navigate to beverages page",
            "match": {
              "location": "us.buyget.step_definitions.mainPageTopTabs.i_should_be_able_to_navigate_to_beverages_page()"
            },
            "keyword": "Then "
          }
        ],
        "tags": [
          {
            "name": "@smoke"
          }
        ]
      },
      {
        "line": 5,
        "name": "",
        "description": "",
        "type": "background",
        "keyword": "Background",
        "steps": [
          {
            "result": {
              "duration": 1139492000,
              "status": "passed"
            },
            "line": 6,
            "name": "I am on the main page",
            "match": {
              "location": "us.buyget.step_definitions.mainPageTopTabs.i_am_on_the_main_page()"
            },
            "keyword": "Given "
          }
        ]
      },
      {
        "start_timestamp": "2021-12-11T18:31:13.086Z",
        "line": 40,
        "name": "",
        "description": "",
        "id": "main-page-top-tabs-functionality;",
        "type": "scenario",
        "keyword": "Scenario",
        "steps": [
          {
            "result": {
              "duration": 354249000,
              "status": "passed"
            },
            "line": 41,
            "name": "I click on the Breads \u0026 Pastries tab",
            "match": {
              "location": "us.buyget.step_definitions.mainPageTopTabs.i_click_on_the_breads_pastries_tab()"
            },
            "keyword": "When "
          },
          {
            "result": {
              "duration": 33084000,
              "status": "passed"
            },
            "line": 42,
            "name": "I should be able to navigate to breads-pastries page",
            "match": {
              "location": "us.buyget.step_definitions.mainPageTopTabs.i_should_be_able_to_navigate_to_breads_pastries_page()"
            },
            "keyword": "Then "
          }
        ],
        "tags": [
          {
            "name": "@smoke"
          }
        ]
      },
      {
        "line": 5,
        "name": "",
        "description": "",
        "type": "background",
        "keyword": "Background",
        "steps": [
          {
            "result": {
              "duration": 1286038000,
              "status": "passed"
            },
            "line": 6,
            "name": "I am on the main page",
            "match": {
              "location": "us.buyget.step_definitions.mainPageTopTabs.i_am_on_the_main_page()"
            },
            "keyword": "Given "
          }
        ]
      },
      {
        "start_timestamp": "2021-12-11T18:31:14.616Z",
        "line": 44,
        "name": "",
        "description": "",
        "id": "main-page-top-tabs-functionality;",
        "type": "scenario",
        "keyword": "Scenario",
        "steps": [
          {
            "result": {
              "duration": 858889000,
              "status": "passed"
            },
            "line": 45,
            "name": "I click on the Brands tab",
            "match": {
              "location": "us.buyget.step_definitions.mainPageTopTabs.i_click_on_the_brands_tab()"
            },
            "keyword": "When "
          },
          {
            "result": {
              "duration": 18578000,
              "status": "passed"
            },
            "line": 46,
            "name": "I should be able to navigate to brands page",
            "match": {
              "location": "us.buyget.step_definitions.mainPageTopTabs.i_should_be_able_to_navigate_to_brands_page()"
            },
            "keyword": "Then "
          }
        ],
        "tags": [
          {
            "name": "@smoke"
          }
        ]
      },
      {
        "line": 5,
        "name": "",
        "description": "",
        "type": "background",
        "keyword": "Background",
        "steps": [
          {
            "result": {
              "duration": 1167137000,
              "status": "passed"
            },
            "line": 6,
            "name": "I am on the main page",
            "match": {
              "location": "us.buyget.step_definitions.mainPageTopTabs.i_am_on_the_main_page()"
            },
            "keyword": "Given "
          }
        ]
      },
      {
        "start_timestamp": "2021-12-11T18:31:16.782Z",
        "line": 48,
        "name": "",
        "description": "",
        "id": "main-page-top-tabs-functionality;",
        "type": "scenario",
        "keyword": "Scenario",
        "steps": [
          {
            "result": {
              "duration": 1094490000,
              "status": "passed"
            },
            "line": 49,
            "name": "I click on the Frozen tab",
            "match": {
              "location": "us.buyget.step_definitions.mainPageTopTabs.i_click_on_the_frozen_tab()"
            },
            "keyword": "When "
          },
          {
            "result": {
              "duration": 18958000,
              "status": "passed"
            },
            "line": 50,
            "name": "I should be able to navigate to frozen page",
            "match": {
              "location": "us.buyget.step_definitions.mainPageTopTabs.i_should_be_able_to_navigate_to_frozen_page()"
            },
            "keyword": "Then "
          }
        ],
        "tags": [
          {
            "name": "@smoke"
          }
        ]
      },
      {
        "line": 5,
        "name": "",
        "description": "",
        "type": "background",
        "keyword": "Background",
        "steps": [
          {
            "result": {
              "duration": 1154879000,
              "status": "passed"
            },
            "line": 6,
            "name": "I am on the main page",
            "match": {
              "location": "us.buyget.step_definitions.mainPageTopTabs.i_am_on_the_main_page()"
            },
            "keyword": "Given "
          }
        ]
      },
      {
        "start_timestamp": "2021-12-11T18:31:19.066Z",
        "line": 52,
        "name": "",
        "description": "",
        "id": "main-page-top-tabs-functionality;",
        "type": "scenario",
        "keyword": "Scenario",
        "steps": [
          {
            "result": {
              "duration": 1346918000,
              "status": "passed"
            },
            "line": 53,
            "name": "I click on the Enjoying Halalcart tab",
            "match": {
              "location": "us.buyget.step_definitions.mainPageTopTabs.i_click_on_the_enjoying_halalcart_tab()"
            },
            "keyword": "When "
          },
          {
            "result": {
              "duration": 11965000,
              "status": "passed"
            },
            "line": 54,
            "name": "I should be able to navigate to invite  page",
            "match": {
              "location": "us.buyget.step_definitions.mainPageTopTabs.i_should_be_able_to_navigate_to_invite_page()"
            },
            "keyword": "Then "
          }
        ],
        "tags": [
          {
            "name": "@smoke"
          }
        ]
      }
    ],
    "name": "Main page top tabs functionality",
    "description": "  As a user, when I click on the top tabs I should be able to access to these particular item pages.",
    "id": "main-page-top-tabs-functionality",
    "keyword": "Feature",
    "uri": "file:src/test/resources/features/mainPageTopTabs.feature",
    "tags": []
  }
]